pycounts_ys/__init__.py
pycounts_ys/plotting.py
pycounts_ys/pycounts.py
pycounts_ys-0.1.0.dist-info/LICENSE
pycounts_ys-0.1.0.dist-info/METADATA
pycounts_ys-0.1.0.dist-info/WHEEL
pycounts_ys-0.1.0.dist-info/RECORD
